pyforce/__init__.py
pyforce/annotations.py
pyforce_plot-0.1.1.dist-info/licenses/LICENSE
pyforce_plot-0.1.1.dist-info/METADATA
pyforce_plot-0.1.1.dist-info/WHEEL
pyforce_plot-0.1.1.dist-info/top_level.txt
pyforce_plot-0.1.1.dist-info/RECORD
