Metadata-Version: 2.4
Name: pyforce-plot
Version: 0.1.1
Summary: Python implementation of ggforce-style annotations for matplotlib
Author-email: Albert Ying <albert.ying@example.com>
License-Expression: MIT
Project-URL: Homepage, https://github.com/albert-ying/pyforce
Project-URL: Documentation, https://github.com/albert-ying/pyforce#readme
Project-URL: Repository, https://github.com/albert-ying/pyforce
Project-URL: Issues, https://github.com/albert-ying/pyforce/issues
Keywords: matplotlib,visualization,annotations,ggplot,ggforce,convex-hull,label-repel
Classifier: Development Status :: 4 - Beta
Classifier: Intended Audience :: Science/Research
Classifier: Operating System :: OS Independent
Classifier: Programming Language :: Python :: 3
Classifier: Programming Language :: Python :: 3.8
Classifier: Programming Language :: Python :: 3.9
Classifier: Programming Language :: Python :: 3.10
Classifier: Programming Language :: Python :: 3.11
Classifier: Programming Language :: Python :: 3.12
Classifier: Topic :: Scientific/Engineering :: Visualization
Requires-Python: >=3.8
License-File: LICENSE
Requires-Dist: numpy>=1.20.0
Requires-Dist: matplotlib>=3.5.0
Requires-Dist: scipy>=1.7.0
Requires-Dist: adjustText>=0.8
Provides-Extra: dev
Requires-Dist: pytest>=7.0; extra == "dev"
Requires-Dist: pytest-cov>=4.0; extra == "dev"
Requires-Dist: black>=22.0; extra == "dev"
Requires-Dist: ruff>=0.0.270; extra == "dev"
Dynamic: license-file
